pysitcom/Comet.py
pysitcom/Sitcom.py
pysitcom/__init__.py
pysitcom/similarity.py
pysitcom-0.1.0.dist-info/LICENCE.txt
pysitcom-0.1.0.dist-info/METADATA
pysitcom-0.1.0.dist-info/WHEEL
pysitcom-0.1.0.dist-info/top_level.txt
pysitcom-0.1.0.dist-info/RECORD
